persons_model/__init__.py
persons_model/common.py
persons_model/config.py
persons_model/context.py
persons_model/country.py
persons_model/individual.py
persons_model/person_entity.py
persons_model/role.py
persons_model/tag.py
sysnet_persons_model-1.1.7.dist-info/licenses/LICENSE
sysnet_persons_model-1.1.7.dist-info/METADATA
sysnet_persons_model-1.1.7.dist-info/WHEEL
sysnet_persons_model-1.1.7.dist-info/top_level.txt
sysnet_persons_model-1.1.7.dist-info/RECORD
