Metadata-Version: 2.4
Name: sysnet-persons-model
Version: 1.1.7
Summary: CITES Data Model
Author-email: Data Developer <info@sysnet.cz>
Project-URL: Homepage, https://github.com/SYSNET-CZ/models/tree/main/persons
Classifier: Development Status :: 4 - Beta
Classifier: Programming Language :: Python :: 3
Classifier: Intended Audience :: Developers
Classifier: License :: Free For Home Use
Classifier: Natural Language :: Czech
Classifier: Operating System :: OS Independent
Classifier: Topic :: Software Development :: Libraries
Requires-Python: >=3.10
License-File: LICENSE
Requires-Dist: sysnet-pyutils>=1.3.4
Requires-Dist: pydantic[email]>=2.11.4
Dynamic: license-file
